polarspiper/__init__.py
polarspiper/polarspiper.py
polarspiper-0.4.0.dist-info/LICENSE
polarspiper-0.4.0.dist-info/METADATA
polarspiper-0.4.0.dist-info/WHEEL
polarspiper-0.4.0.dist-info/RECORD
