Metadata-Version: 2.1
Name: polarspiper
Version: 0.4.0
Summary: 
Home-page: https://github.com/thomascamminady/piper
Author: Thomas Camminady
Author-email: 0milieux_member@icloud.com
Requires-Python: >=3.11,<3.13
Classifier: Programming Language :: Python :: 3
Classifier: Programming Language :: Python :: 3.11
Classifier: Programming Language :: Python :: 3.12
Requires-Dist: polars (>=1.12.0,<2.0.0)
Project-URL: Documentation, https://thomascamminady.github.io/piper
Project-URL: Repository, https://github.com/thomascamminady/piper
